xaal/__init__.py
xaal/fakeinput/__init__.py
xaal/fakeinput/__main__.py
xaal/fakeinput/app.py
xaal/fakeinput/devices.py
xaal/fakeinput/static/Play-Regular.ttf
xaal/fakeinput/static/jquery.min.js
xaal/fakeinput/static/site.js
xaal/fakeinput/static/style.css
xaal/fakeinput/views/index.tpl
xaal_fakeinput-0.4.4.dist-info/METADATA
xaal_fakeinput-0.4.4.dist-info/WHEEL
xaal_fakeinput-0.4.4.dist-info/top_level.txt
xaal_fakeinput-0.4.4.dist-info/RECORD
