Metadata-Version: 2.4
Name: xaal.fakeinput
Version: 0.4.4
Summary: xAAL fake switch, buttons, contact devices 
Author-email: Jerome Kerdreux <Jerome.Kerdreux@imt-atlantique.fr>
License-Expression: GPL-3.0-or-later
Project-URL: Homepage, https://recherche.imt-atlantique.fr/xaal/
Project-URL: Documentation, https://gitlab.imt-atlantique.fr/xaal/code/python/-/blob/main/devices/tests/fakeinput/README.rst
Project-URL: Source, https://gitlab.imt-atlantique.fr/xaal/code/python/-/tree/main/devices/tests/fakeinput
Keywords: xaal,json
Classifier: Programming Language :: Python
Classifier: Topic :: Home Automation
Requires-Dist: xaal.lib
Requires-Dist: xaal.schemas
Requires-Dist: bottle
Requires-Dist: gevent
Requires-Dist: gevent-websocket
